craterslab/__init__.py
craterslab/classification.py
craterslab/craters.py
craterslab/craterslab.weights.h5
craterslab/ellipse.py
craterslab/images.py
craterslab/profiles.py
craterslab/sensors.py
craterslab/visuals.py
craterslab-0.2.8.dist-info/LICENSE
craterslab-0.2.8.dist-info/METADATA
craterslab-0.2.8.dist-info/WHEEL
craterslab-0.2.8.dist-info/RECORD
