Metadata-Version: 2.3
Name: craterslab
Version: 0.2.8
Summary: 
License: MIT
Keywords: craters,depth maps,lidar,impacts
Author: Gustavo Viera López
Author-email: gvieralopez@gmail.com
Requires-Python: >=3.10
Classifier: Intended Audience :: Science/Research
Classifier: License :: OSI Approved :: MIT License
Classifier: Programming Language :: Python :: 3
Classifier: Programming Language :: Python :: 3.10
Classifier: Programming Language :: Python :: 3.11
Classifier: Programming Language :: Python :: 3.12
Classifier: Programming Language :: Python :: 3.13
Requires-Dist: keras (>=3.0.0)
Requires-Dist: matplotlib (>=3.7.2,<4.0.0)
Requires-Dist: numpy (>=1.24.0,<2.0.0)
Requires-Dist: opencv-python (>=4.8.0,<5.0.0)
Requires-Dist: scikit-learn (>=1.3.0,<2.0.0)
Requires-Dist: scipy (>=1.11.1,<2.0.0)
Requires-Dist: tensorflow (>=2.13.0)
Project-URL: Documentation, https://craterslab.readthedocs.io/en/latest/
Project-URL: Homepage, https://github.com/gvieralopez/craters
Project-URL: Repository, https://github.com/gvieralopez/craters
